[
    {
      "_id": "64fffd6d7fc89d3928641ec4",
      "project_manager": "Farhan Rahman",
      "no_of_project": 18,
      "total_project_value": "$21,600.00",
      "total_released_amount": "$12,673.50",
      "no_of_completed_project": 10,
      "no_of_completed_project_without_authorization": 4,
      "project_completion_rate": 79,
      "project_completion_rate_without_authorization": 83,
      "no_of_first_time_clients": 4,
      "milestone_completion_rate": 78,
      "task_completion_rate": "85%",
      "average_project_completion_time": "07 Days 18 Hours 39 Minutes",
      "no_of_sale": "5 / 4",
      "value_of_sale": "$5500.00 / $4258.00",
      "canceled_projects": 2,
      "delayed_projects": 8,
      "delayed_completed": 7,
      "percentage_of_delayed_projects": 15,
      "canelation_rate": 13,
      "avg_payment_rel_time": 3.2
    },
    {
      "_id": "64fffd6d6db95eee10e9f696",
      "project_manager": "Dinar M Islam",
      "no_of_project": 21,
      "total_project_value": "$25,200.00",
      "total_released_amount": "$15,975.50",
      "no_of_completed_project": 13,
      "no_of_completed_project_without_authorization": 3,
      "project_completion_rate": 83,
      "project_completion_rate_without_authorization": 86,
      "no_of_first_time_clients": 11,
      "milestone_completion_rate": 88,
      "task_completion_rate": "92%",
      "average_project_completion_time": "09 Days 05 Hours 55 Minutes",
      "no_of_sale": "4 / 6",
      "value_of_sale": "$ 4,890.00",
      "canceled_projects": 2,
      "delayed_projects": 6,
      "delayed_completed": 6,
      "percentage_of_delayed_projects": 15,
      "canelation_rate": 13,
      "avg_payment_rel_time": 3.2
    },
    {
      "_id": "64fffd6d1621ac37dc561e18",
      "project_manager": "Mohammad Fazle Rabbi",
      "no_of_project": 24,
      "total_project_value": "$28,800.00",
      "total_released_amount": "$19,510.80",
      "no_of_completed_project": 15,
      "no_of_completed_project_without_authorization": 4,
      "project_completion_rate": "85%",
      "project_completion_rate_without_authorization": "92%",
      "no_of_first_time_clients": 13,
      "milestone_completion_rate": "69%",
      "task_completion_rate": "89%",
      "average_project_completion_time": "11 Days 15 Hours 29 Minutes",
      "no_of_sale": "10 / 7",
      "value_of_sale": "$8250.00 / $4550.00",
      "canceled_projects": 3,
      "delayed_projects": 11,
      "delayed_completed": 8,
      "percentage_of_delayed_projects": 15,
      "canelation_rate": 13,
      "avg_payment_rel_time": 3.2
    },
    {
      "_id": "64fffd6d7fc89d3928641ec5",
      "project_manager": "Farhan Rahman",
      "no_of_project": 18,
      "total_project_value": "$21,600.00",
      "total_released_amount": "$12,673.50",
      "no_of_completed_project": 10,
      "no_of_completed_project_without_authorization": 4,
      "project_completion_rate": 79,
      "project_completion_rate_without_authorization": 83,
      "no_of_first_time_clients": 4,
      "milestone_completion_rate": 78,
      "task_completion_rate": "85%",
      "average_project_completion_time": "07 Days 18 Hours 39 Minutes",
      "no_of_sale": "5 / 4",
      "value_of_sale": "$5500.00 / $4258.00",
      "canceled_projects": 2,
      "delayed_projects": 8,
      "delayed_completed": 7,
      "percentage_of_delayed_projects": 15,
      "canelation_rate": 13,
      "avg_payment_rel_time": 3.2
    },
    {
      "_id": "64fffd6d6db95eee10e9f697",
      "project_manager": "Dinar M Islam",
      "no_of_project": 21,
      "total_project_value": "$25,200.00",
      "total_released_amount": "$15,975.50",
      "no_of_completed_project": 13,
      "no_of_completed_project_without_authorization": 3,
      "project_completion_rate": 83,
      "project_completion_rate_without_authorization": 86,
      "no_of_first_time_clients": 11,
      "milestone_completion_rate": 88,
      "task_completion_rate": "92%",
      "average_project_completion_time": "09 Days 05 Hours 55 Minutes",
      "no_of_sale": "4 / 6",
      "value_of_sale": "$ 4,890.00",
      "canceled_projects": 2,
      "delayed_projects": 6,
      "delayed_completed": 6,
      "percentage_of_delayed_projects": 15,
      "canelation_rate": 13,
      "avg_payment_rel_time": 3.2
    },
    {
      "_id": "64fffd6d1621ac37dc561e19",
      "project_manager": "Mohammad Fazle Rabbi",
      "no_of_project": 24,
      "total_project_value": "$28,800.00",
      "total_released_amount": "$19,510.80",
      "no_of_completed_project": 15,
      "no_of_completed_project_without_authorization": 4,
      "project_completion_rate": "85%",
      "project_completion_rate_without_authorization": "92%",
      "no_of_first_time_clients": 13,
      "milestone_completion_rate": "69%",
      "task_completion_rate": "89%",
      "average_project_completion_time": "11 Days 15 Hours 29 Minutes",
      "no_of_sale": "10 / 7",
      "value_of_sale": "$8250.00 / $4550.00",
      "canceled_projects": 3,
      "delayed_projects": 11,
      "delayed_completed": 8,
      "percentage_of_delayed_projects": 15,
      "canelation_rate": 13,
      "avg_payment_rel_time": 3.2
    },
    {
      "_id": "64fffd6d7fc89d3928641ec6",
      "project_manager": "Farhan Rahman",
      "no_of_project": 18,
      "total_project_value": "$21,600.00",
      "total_released_amount": "$12,673.50",
      "no_of_completed_project": 10,
      "no_of_completed_project_without_authorization": 4,
      "project_completion_rate": 79,
      "project_completion_rate_without_authorization": 83,
      "no_of_first_time_clients": 4,
      "milestone_completion_rate": 78,
      "task_completion_rate": "85%",
      "average_project_completion_time": "07 Days 18 Hours 39 Minutes",
      "no_of_sale": "5 / 4",
      "value_of_sale": "$5500.00 / $4258.00",
      "canceled_projects": 2,
      "delayed_projects": 8,
      "delayed_completed": 7,
      "percentage_of_delayed_projects": 15,
      "canelation_rate": 13,
      "avg_payment_rel_time": 3.2
    },
    {
      "_id": "64fffd6d6db95eee10e9f698",
      "project_manager": "Dinar M Islam",
      "no_of_project": 21,
      "total_project_value": "$25,200.00",
      "total_released_amount": "$15,975.50",
      "no_of_completed_project": 13,
      "no_of_completed_project_without_authorization": 3,
      "project_completion_rate": 83,
      "project_completion_rate_without_authorization": 86,
      "no_of_first_time_clients": 11,
      "milestone_completion_rate": 88,
      "task_completion_rate": "92%",
      "average_project_completion_time": "09 Days 05 Hours 55 Minutes",
      "no_of_sale": "4 / 6",
      "value_of_sale": "$ 4,890.00",
      "canceled_projects": 2,
      "delayed_projects": 6,
      "delayed_completed": 6,
      "percentage_of_delayed_projects": 15,
      "canelation_rate": 13,
      "avg_payment_rel_time": 3.2
    },
    {
      "_id": "64fffd6d1621ac37dc561e20",
      "project_manager": "Mohammad Fazle Rabbi",
      "no_of_project": 24,
      "total_project_value": "$28,800.00",
      "total_released_amount": "$19,510.80",
      "no_of_completed_project": 15,
      "no_of_completed_project_without_authorization": 4,
      "project_completion_rate": "85%",
      "project_completion_rate_without_authorization": "92%",
      "no_of_first_time_clients": 13,
      "milestone_completion_rate": "69%",
      "task_completion_rate": "89%",
      "average_project_completion_time": "11 Days 15 Hours 29 Minutes",
      "no_of_sale": "10 / 7",
      "value_of_sale": "$8250.00 / $4550.00",
      "canceled_projects": 3,
      "delayed_projects": 11,
      "delayed_completed": 8,
      "percentage_of_delayed_projects": "15%",
      "canelation_rate": "13%",
      "avg_payment_rel_time": "3.2/Day"
    }
  ]